<?xml version="1.0" encoding="utf-8"?>
<association id="1f85360e-7bda-41e3-a321-f1fca8705909">
  <sourceEnd id="d305c726-0520-469a-9d2d-691111a37df6" type="Association Source End" typeId="8d9d2e5b-bd55-4f36-9ae4-2b9e84fd4e58">
    <name>Events</name>
    <display>Events: Event[*]</display>
    <order>14</order>
    <typeReference id="a7dccfba-5327-4b29-9d57-fb582c07d3ab">
      <typeId>d5677f67-60a8-4400-8156-86c589f0436f</typeId>
      <isNavigable>false</isNavigable>
      <isNullable>false</isNullable>
      <isCollection>true</isCollection>
      <isRequired>true</isRequired>
      <typePackageName>Boxfusion.Dep</typePackageName>
      <typePackageId>f7adeae6-ee51-4270-83fb-2b44a50da39b</typePackageId>
      <stereotypes />
      <genericTypeParameters />
    </typeReference>
    <stereotypes />
    <metadata />
  </sourceEnd>
  <targetEnd id="1f85360e-7bda-41e3-a321-f1fca8705909" type="Association Target End" typeId="0a66489f-30aa-417b-a75d-b945863366fd">
    <name>EventImage</name>
    <display>EventImage: StoredFile</display>
    <order>11</order>
    <typeReference id="8a3bec54-b876-4d4b-a894-d2d2de3c7207">
      <typeId>a84572a0-9354-4dc5-84c6-df6d496a7790</typeId>
      <isNavigable>true</isNavigable>
      <isNullable>false</isNullable>
      <isCollection>false</isCollection>
      <isRequired>true</isRequired>
      <typePackageName>Shesha.Core</typePackageName>
      <typePackageId>9429b641-0f6e-4da5-a76d-6e9d7d34eab8</typePackageId>
      <stereotypes />
      <genericTypeParameters />
    </typeReference>
    <stereotypes />
    <metadata />
  </targetEnd>
  <associationType>Association</associationType>
  <associationTypeId>eaf9ed4e-0b61-4ac1-ba88-09f912c12087</associationTypeId>
  <stereotypes />
</association>