<?xml version="1.0" encoding="utf-8"?>
<class id="da9bc02b-ef60-412d-be15-e3e5f417c74d" type="Class" typeId="04e12b51-ed12-42a3-9667-a6aa81bb6d10">
  <name>ContentItemBase</name>
  <display>ContentItemBase</display>
  <isAbstract>false</isAbstract>
  <sort-children>by-type-then-manually</sort-children>
  <genericTypes />
  <isMapped>false</isMapped>
  <parentFolderId>bdd4019a-34d4-4435-8ad9-02d6f6a58acf</parentFolderId>
  <packageId>b3a6eff9-3147-4a21-b90b-91b9d4a0e02a</packageId>
  <packageName>Boxfusion.ContentManagement</packageName>
  <stereotypes>
    <stereotype stereotypeDefinitionId="3416ad21-0091-4240-957e-a3ab84bc99d5" name="Full Audited">
      <addedByDefault>true</addedByDefault>
      <definitionPackageName>Boxfusion.Modules.Domain</definitionPackageName>
      <definitionPackageId>adb17c92-23cd-47f7-beeb-99512b09467b</definitionPackageId>
      <properties />
    </stereotype>
    <stereotype stereotypeDefinitionId="64a1e48f-80e9-49f7-8d32-c048fd05ef59" name="Entity Settings">
      <addedByDefault>true</addedByDefault>
      <definitionPackageName>Boxfusion.Modules.Domain</definitionPackageName>
      <definitionPackageId>adb17c92-23cd-47f7-beeb-99512b09467b</definitionPackageId>
      <properties>
        <property name="83554d31-64cf-4a73-8566-8db8f1eea802" display="Type Short Alias" isActive="true" />
        <property name="f7c6c2ea-a7d8-482d-895d-951fa560f2b8" display="Friendly Name" value="" isActive="true" />
        <property name="80ce011d-22b1-44dd-b24e-bc77d388b26e" display="Generate Application Service" value="true" isActive="true" />
        <property name="215f896f-cf59-422e-9f14-9c12a925f538" display="Application Service Name" isActive="true" />
        <property name="08d757f1-f64d-4f48-b798-244f443172c9" display="Status" value="Req. Ready" isActive="true" />
      </properties>
    </stereotype>
  </stereotypes>
  <metadata />
  <childElements>
    <childElement id="42db0676-01b4-4930-aff9-c0bbc998cdf7" type="Attribute" typeId="0090fb93-483e-41af-a11d-5ad2dc796adf">
      <name>ImageIconUrl</name>
      <display>ImageIconUrl: string</display>
      <isAbstract>false</isAbstract>
      <genericTypes />
      <typeReference id="a37c5b50-9bf6-44df-bd75-28684b0abf0c">
        <typeId>d384db9c-a279-45e1-801e-e4e8099625f2</typeId>
        <isNavigable>true</isNavigable>
        <isNullable>false</isNullable>
        <isCollection>false</isCollection>
        <isRequired>true</isRequired>
        <typePackageName>Intent.Common.Types</typePackageName>
        <typePackageId>870ad967-cbd4-4ea9-b86d-9c3a5d55ea67</typePackageId>
        <stereotypes />
        <genericTypeParameters />
      </typeReference>
      <isMapped>false</isMapped>
      <parentFolderId>da9bc02b-ef60-412d-be15-e3e5f417c74d</parentFolderId>
      <packageId>b3a6eff9-3147-4a21-b90b-91b9d4a0e02a</packageId>
      <packageName>Boxfusion.ContentManagement</packageName>
      <stereotypes>
        <stereotype stereotypeDefinitionId="34163c46-790f-4b68-a3b7-3b92b5c78885" name="Attribute Settings">
          <addedByDefault>true</addedByDefault>
          <definitionPackageName>Boxfusion.Modules.Domain</definitionPackageName>
          <definitionPackageId>adb17c92-23cd-47f7-beeb-99512b09467b</definitionPackageId>
          <properties>
            <property name="c0114451-8a23-46c3-b4b5-b95f696d885e" display="IsRequired" value="false" isActive="true" />
            <property name="3db8e495-52c6-452a-8a44-91a9213947a7" display="LogChanges" value="false" isActive="true" />
            <property name="cd14ac60-5753-44fa-8be9-4228975552b4" display="ReadOnly" value="false" isActive="true" />
            <property name="4c7bf420-18ea-4fa8-aa9b-c63fb9a07848" display="DisplayName" isActive="true" />
            <property name="3cc97725-8916-4c85-9c65-cd5ec3a0bd66" display="Status" value="Req. Ready" isActive="true" />
            <property name="764a44c9-4e2b-4486-bd91-f3b412d32d9f" display="CustomRegExValidation" isActive="true" />
            <property name="d42cd351-3f91-4833-a43e-7d681ab43391" display="CustomValidationMessage" isActive="true" />
            <property name="38112123-4582-4386-86cf-8b693de6d84d" display="Setter Access" isActive="true" />
            <property name="34654eff-761e-4a7c-b216-03f99206c6b5" display="Getter Access" isActive="true" />
          </properties>
        </stereotype>
        <stereotype stereotypeDefinitionId="6347286E-A637-44D6-A5D7-D9BE5789CA7A" name="Text Constraints">
          <addedByDefault>true</addedByDefault>
          <definitionPackageName>Intent.Metadata.RDBMS</definitionPackageName>
          <definitionPackageId>AF8F3810-745C-42A2-93C8-798860DC45B1</definitionPackageId>
          <properties>
            <property name="1288cfcd-ee51-437e-9713-73b80118f026" display="SQL Data Type" value="DEFAULT" isActive="true" />
            <property name="A04CC24D-81FB-4EA2-A34A-B3C58E04DCFD" display="MaxLength" isActive="true" />
            <property name="67EC4CF4-7706-4B39-BC7C-DF539EE2B0AF" display="IsUnicode" value="false" isActive="true" />
          </properties>
        </stereotype>
      </stereotypes>
      <metadata />
      <childElements />
    </childElement>
    <childElement id="ac6dbb13-c2fb-48f2-be5c-04edb681a53f" type="Attribute" typeId="0090fb93-483e-41af-a11d-5ad2dc796adf">
      <name>AllowLiking</name>
      <display>AllowLiking: bool</display>
      <isAbstract>false</isAbstract>
      <genericTypes />
      <typeReference id="765a5b35-17d7-400a-9cc0-98e8c03a9841">
        <typeId>e6f92b09-b2c5-4536-8270-a4d9e5bbd930</typeId>
        <isNavigable>true</isNavigable>
        <isNullable>false</isNullable>
        <isCollection>false</isCollection>
        <isRequired>true</isRequired>
        <typePackageName>Intent.Common.Types</typePackageName>
        <typePackageId>870ad967-cbd4-4ea9-b86d-9c3a5d55ea67</typePackageId>
        <stereotypes />
        <genericTypeParameters />
      </typeReference>
      <isMapped>false</isMapped>
      <parentFolderId>da9bc02b-ef60-412d-be15-e3e5f417c74d</parentFolderId>
      <packageId>b3a6eff9-3147-4a21-b90b-91b9d4a0e02a</packageId>
      <packageName>Boxfusion.ContentManagement</packageName>
      <stereotypes>
        <stereotype stereotypeDefinitionId="34163c46-790f-4b68-a3b7-3b92b5c78885" name="Attribute Settings">
          <addedByDefault>true</addedByDefault>
          <definitionPackageName>Boxfusion.Modules.Domain</definitionPackageName>
          <definitionPackageId>adb17c92-23cd-47f7-beeb-99512b09467b</definitionPackageId>
          <properties>
            <property name="c0114451-8a23-46c3-b4b5-b95f696d885e" display="IsRequired" value="false" isActive="true" />
            <property name="3db8e495-52c6-452a-8a44-91a9213947a7" display="LogChanges" value="false" isActive="true" />
            <property name="cd14ac60-5753-44fa-8be9-4228975552b4" display="ReadOnly" value="false" isActive="true" />
            <property name="4c7bf420-18ea-4fa8-aa9b-c63fb9a07848" display="DisplayName" isActive="true" />
            <property name="3cc97725-8916-4c85-9c65-cd5ec3a0bd66" display="Status" value="Req. Ready" isActive="true" />
            <property name="764a44c9-4e2b-4486-bd91-f3b412d32d9f" display="CustomRegExValidation" isActive="true" />
            <property name="d42cd351-3f91-4833-a43e-7d681ab43391" display="CustomValidationMessage" isActive="true" />
            <property name="38112123-4582-4386-86cf-8b693de6d84d" display="Setter Access" isActive="true" />
            <property name="34654eff-761e-4a7c-b216-03f99206c6b5" display="Getter Access" isActive="true" />
          </properties>
        </stereotype>
      </stereotypes>
      <metadata />
      <childElements />
    </childElement>
    <childElement id="292c47a5-3721-4f88-b0d1-200b3b305e89" type="Attribute" typeId="0090fb93-483e-41af-a11d-5ad2dc796adf">
      <name>AllowCommenting</name>
      <display>AllowCommenting: bool</display>
      <isAbstract>false</isAbstract>
      <genericTypes />
      <typeReference id="a4aa481c-1227-4b08-a88f-9d09c89ce8eb">
        <typeId>e6f92b09-b2c5-4536-8270-a4d9e5bbd930</typeId>
        <isNavigable>true</isNavigable>
        <isNullable>false</isNullable>
        <isCollection>false</isCollection>
        <isRequired>true</isRequired>
        <typePackageName>Intent.Common.Types</typePackageName>
        <typePackageId>870ad967-cbd4-4ea9-b86d-9c3a5d55ea67</typePackageId>
        <stereotypes />
        <genericTypeParameters />
      </typeReference>
      <isMapped>false</isMapped>
      <parentFolderId>da9bc02b-ef60-412d-be15-e3e5f417c74d</parentFolderId>
      <packageId>b3a6eff9-3147-4a21-b90b-91b9d4a0e02a</packageId>
      <packageName>Boxfusion.ContentManagement</packageName>
      <stereotypes>
        <stereotype stereotypeDefinitionId="34163c46-790f-4b68-a3b7-3b92b5c78885" name="Attribute Settings">
          <addedByDefault>true</addedByDefault>
          <definitionPackageName>Boxfusion.Modules.Domain</definitionPackageName>
          <definitionPackageId>adb17c92-23cd-47f7-beeb-99512b09467b</definitionPackageId>
          <properties>
            <property name="c0114451-8a23-46c3-b4b5-b95f696d885e" display="IsRequired" value="false" isActive="true" />
            <property name="3db8e495-52c6-452a-8a44-91a9213947a7" display="LogChanges" value="false" isActive="true" />
            <property name="cd14ac60-5753-44fa-8be9-4228975552b4" display="ReadOnly" value="false" isActive="true" />
            <property name="4c7bf420-18ea-4fa8-aa9b-c63fb9a07848" display="DisplayName" isActive="true" />
            <property name="3cc97725-8916-4c85-9c65-cd5ec3a0bd66" display="Status" value="Req. Ready" isActive="true" />
            <property name="764a44c9-4e2b-4486-bd91-f3b412d32d9f" display="CustomRegExValidation" isActive="true" />
            <property name="d42cd351-3f91-4833-a43e-7d681ab43391" display="CustomValidationMessage" isActive="true" />
            <property name="38112123-4582-4386-86cf-8b693de6d84d" display="Setter Access" isActive="true" />
            <property name="34654eff-761e-4a7c-b216-03f99206c6b5" display="Getter Access" isActive="true" />
          </properties>
        </stereotype>
      </stereotypes>
      <metadata />
      <childElements />
    </childElement>
    <childElement id="a2f69dbb-c114-4e30-b7c7-fd87954d6989" type="Attribute" typeId="0090fb93-483e-41af-a11d-5ad2dc796adf">
      <name>ValidFrom</name>
      <display>ValidFrom: datetime</display>
      <isAbstract>false</isAbstract>
      <genericTypes />
      <typeReference id="5ff07e0c-99b0-4e4e-9d3d-cfab8e1e1292">
        <typeId>a4107c29-7851-4121-9416-cf1236908f1e</typeId>
        <isNavigable>true</isNavigable>
        <isNullable>false</isNullable>
        <isCollection>false</isCollection>
        <isRequired>true</isRequired>
        <typePackageName>Intent.Common.Types</typePackageName>
        <typePackageId>870ad967-cbd4-4ea9-b86d-9c3a5d55ea67</typePackageId>
        <stereotypes />
        <genericTypeParameters />
      </typeReference>
      <isMapped>false</isMapped>
      <parentFolderId>da9bc02b-ef60-412d-be15-e3e5f417c74d</parentFolderId>
      <packageId>b3a6eff9-3147-4a21-b90b-91b9d4a0e02a</packageId>
      <packageName>Boxfusion.ContentManagement</packageName>
      <stereotypes>
        <stereotype stereotypeDefinitionId="34163c46-790f-4b68-a3b7-3b92b5c78885" name="Attribute Settings">
          <addedByDefault>true</addedByDefault>
          <definitionPackageName>Boxfusion.Modules.Domain</definitionPackageName>
          <definitionPackageId>adb17c92-23cd-47f7-beeb-99512b09467b</definitionPackageId>
          <properties>
            <property name="c0114451-8a23-46c3-b4b5-b95f696d885e" display="IsRequired" value="false" isActive="true" />
            <property name="3db8e495-52c6-452a-8a44-91a9213947a7" display="LogChanges" value="false" isActive="true" />
            <property name="cd14ac60-5753-44fa-8be9-4228975552b4" display="ReadOnly" value="false" isActive="true" />
            <property name="4c7bf420-18ea-4fa8-aa9b-c63fb9a07848" display="DisplayName" isActive="true" />
            <property name="3cc97725-8916-4c85-9c65-cd5ec3a0bd66" display="Status" value="Req. Ready" isActive="true" />
            <property name="764a44c9-4e2b-4486-bd91-f3b412d32d9f" display="CustomRegExValidation" isActive="true" />
            <property name="d42cd351-3f91-4833-a43e-7d681ab43391" display="CustomValidationMessage" isActive="true" />
            <property name="38112123-4582-4386-86cf-8b693de6d84d" display="Setter Access" isActive="true" />
            <property name="34654eff-761e-4a7c-b216-03f99206c6b5" display="Getter Access" isActive="true" />
          </properties>
        </stereotype>
      </stereotypes>
      <metadata />
      <childElements />
    </childElement>
    <childElement id="e269148d-e4b4-4a6e-afd4-4d2883aff155" type="Attribute" typeId="0090fb93-483e-41af-a11d-5ad2dc796adf">
      <name>ValidTo</name>
      <display>ValidTo: datetime</display>
      <isAbstract>false</isAbstract>
      <genericTypes />
      <typeReference id="559a8469-cd4a-427d-ac92-0107dc927f0b">
        <typeId>a4107c29-7851-4121-9416-cf1236908f1e</typeId>
        <isNavigable>true</isNavigable>
        <isNullable>false</isNullable>
        <isCollection>false</isCollection>
        <isRequired>true</isRequired>
        <typePackageName>Intent.Common.Types</typePackageName>
        <typePackageId>870ad967-cbd4-4ea9-b86d-9c3a5d55ea67</typePackageId>
        <stereotypes />
        <genericTypeParameters />
      </typeReference>
      <isMapped>false</isMapped>
      <parentFolderId>da9bc02b-ef60-412d-be15-e3e5f417c74d</parentFolderId>
      <packageId>b3a6eff9-3147-4a21-b90b-91b9d4a0e02a</packageId>
      <packageName>Boxfusion.ContentManagement</packageName>
      <stereotypes>
        <stereotype stereotypeDefinitionId="34163c46-790f-4b68-a3b7-3b92b5c78885" name="Attribute Settings">
          <addedByDefault>true</addedByDefault>
          <definitionPackageName>Boxfusion.Modules.Domain</definitionPackageName>
          <definitionPackageId>adb17c92-23cd-47f7-beeb-99512b09467b</definitionPackageId>
          <properties>
            <property name="c0114451-8a23-46c3-b4b5-b95f696d885e" display="IsRequired" value="false" isActive="true" />
            <property name="3db8e495-52c6-452a-8a44-91a9213947a7" display="LogChanges" value="false" isActive="true" />
            <property name="cd14ac60-5753-44fa-8be9-4228975552b4" display="ReadOnly" value="false" isActive="true" />
            <property name="4c7bf420-18ea-4fa8-aa9b-c63fb9a07848" display="DisplayName" isActive="true" />
            <property name="3cc97725-8916-4c85-9c65-cd5ec3a0bd66" display="Status" value="Req. Ready" isActive="true" />
            <property name="764a44c9-4e2b-4486-bd91-f3b412d32d9f" display="CustomRegExValidation" isActive="true" />
            <property name="d42cd351-3f91-4833-a43e-7d681ab43391" display="CustomValidationMessage" isActive="true" />
            <property name="38112123-4582-4386-86cf-8b693de6d84d" display="Setter Access" isActive="true" />
            <property name="34654eff-761e-4a7c-b216-03f99206c6b5" display="Getter Access" isActive="true" />
          </properties>
        </stereotype>
      </stereotypes>
      <metadata />
      <childElements />
    </childElement>
    <childElement id="9c6df4a8-9403-4a0c-9f5f-77693e0a318b" type="Attribute" typeId="0090fb93-483e-41af-a11d-5ad2dc796adf">
      <name>CanExport</name>
      <display>CanExport: bool</display>
      <isAbstract>false</isAbstract>
      <genericTypes />
      <typeReference id="9f821b3b-f545-4852-9d11-e0faef1fa328">
        <typeId>e6f92b09-b2c5-4536-8270-a4d9e5bbd930</typeId>
        <isNavigable>true</isNavigable>
        <isNullable>false</isNullable>
        <isCollection>false</isCollection>
        <isRequired>true</isRequired>
        <typePackageName>Intent.Common.Types</typePackageName>
        <typePackageId>870ad967-cbd4-4ea9-b86d-9c3a5d55ea67</typePackageId>
        <stereotypes />
        <genericTypeParameters />
      </typeReference>
      <isMapped>false</isMapped>
      <parentFolderId>da9bc02b-ef60-412d-be15-e3e5f417c74d</parentFolderId>
      <packageId>b3a6eff9-3147-4a21-b90b-91b9d4a0e02a</packageId>
      <packageName>Boxfusion.ContentManagement</packageName>
      <stereotypes>
        <stereotype stereotypeDefinitionId="34163c46-790f-4b68-a3b7-3b92b5c78885" name="Attribute Settings">
          <addedByDefault>true</addedByDefault>
          <definitionPackageName>Boxfusion.Modules.Domain</definitionPackageName>
          <definitionPackageId>adb17c92-23cd-47f7-beeb-99512b09467b</definitionPackageId>
          <properties>
            <property name="c0114451-8a23-46c3-b4b5-b95f696d885e" display="IsRequired" value="false" isActive="true" />
            <property name="3db8e495-52c6-452a-8a44-91a9213947a7" display="LogChanges" value="false" isActive="true" />
            <property name="cd14ac60-5753-44fa-8be9-4228975552b4" display="ReadOnly" value="false" isActive="true" />
            <property name="4c7bf420-18ea-4fa8-aa9b-c63fb9a07848" display="DisplayName" isActive="true" />
            <property name="3cc97725-8916-4c85-9c65-cd5ec3a0bd66" display="Status" value="Req. Ready" isActive="true" />
            <property name="764a44c9-4e2b-4486-bd91-f3b412d32d9f" display="CustomRegExValidation" isActive="true" />
            <property name="d42cd351-3f91-4833-a43e-7d681ab43391" display="CustomValidationMessage" isActive="true" />
            <property name="38112123-4582-4386-86cf-8b693de6d84d" display="Setter Access" isActive="true" />
            <property name="34654eff-761e-4a7c-b216-03f99206c6b5" display="Getter Access" isActive="true" />
          </properties>
        </stereotype>
      </stereotypes>
      <metadata />
      <childElements />
    </childElement>
    <childElement id="e0789964-a4bd-439b-adfc-38a131a2775a" type="Attribute" typeId="0090fb93-483e-41af-a11d-5ad2dc796adf">
      <name>PublishedDate</name>
      <display>PublishedDate: datetime</display>
      <isAbstract>false</isAbstract>
      <genericTypes />
      <typeReference id="361127f5-bed6-4da7-a2aa-8135fb31b93a">
        <typeId>a4107c29-7851-4121-9416-cf1236908f1e</typeId>
        <isNavigable>true</isNavigable>
        <isNullable>false</isNullable>
        <isCollection>false</isCollection>
        <isRequired>true</isRequired>
        <typePackageName>Intent.Common.Types</typePackageName>
        <typePackageId>870ad967-cbd4-4ea9-b86d-9c3a5d55ea67</typePackageId>
        <stereotypes />
        <genericTypeParameters />
      </typeReference>
      <isMapped>false</isMapped>
      <parentFolderId>da9bc02b-ef60-412d-be15-e3e5f417c74d</parentFolderId>
      <packageId>b3a6eff9-3147-4a21-b90b-91b9d4a0e02a</packageId>
      <packageName>Boxfusion.ContentManagement</packageName>
      <stereotypes>
        <stereotype stereotypeDefinitionId="34163c46-790f-4b68-a3b7-3b92b5c78885" name="Attribute Settings">
          <addedByDefault>true</addedByDefault>
          <definitionPackageName>Boxfusion.Modules.Domain</definitionPackageName>
          <definitionPackageId>adb17c92-23cd-47f7-beeb-99512b09467b</definitionPackageId>
          <properties>
            <property name="c0114451-8a23-46c3-b4b5-b95f696d885e" display="IsRequired" value="false" isActive="true" />
            <property name="3db8e495-52c6-452a-8a44-91a9213947a7" display="LogChanges" value="false" isActive="true" />
            <property name="cd14ac60-5753-44fa-8be9-4228975552b4" display="ReadOnly" value="false" isActive="true" />
            <property name="4c7bf420-18ea-4fa8-aa9b-c63fb9a07848" display="DisplayName" isActive="true" />
            <property name="3cc97725-8916-4c85-9c65-cd5ec3a0bd66" display="Status" value="Req. Ready" isActive="true" />
            <property name="764a44c9-4e2b-4486-bd91-f3b412d32d9f" display="CustomRegExValidation" isActive="true" />
            <property name="d42cd351-3f91-4833-a43e-7d681ab43391" display="CustomValidationMessage" isActive="true" />
            <property name="38112123-4582-4386-86cf-8b693de6d84d" display="Setter Access" isActive="true" />
            <property name="34654eff-761e-4a7c-b216-03f99206c6b5" display="Getter Access" isActive="true" />
          </properties>
        </stereotype>
      </stereotypes>
      <metadata />
      <childElements />
    </childElement>
    <childElement id="94b86ea6-84cf-45a5-90f6-35daed05abc4" type="Attribute" typeId="0090fb93-483e-41af-a11d-5ad2dc796adf">
      <name>OrderIndex</name>
      <display>OrderIndex: int</display>
      <isAbstract>false</isAbstract>
      <genericTypes />
      <typeReference id="9b181604-0604-4b8d-ae4b-f8c6a0b9eb25">
        <typeId>fb0a362d-e9e2-40de-b6ff-5ce8167cbe74</typeId>
        <isNavigable>true</isNavigable>
        <isNullable>false</isNullable>
        <isCollection>false</isCollection>
        <isRequired>true</isRequired>
        <typePackageName>Intent.Common.Types</typePackageName>
        <typePackageId>870ad967-cbd4-4ea9-b86d-9c3a5d55ea67</typePackageId>
        <stereotypes />
        <genericTypeParameters />
      </typeReference>
      <isMapped>false</isMapped>
      <parentFolderId>da9bc02b-ef60-412d-be15-e3e5f417c74d</parentFolderId>
      <packageId>b3a6eff9-3147-4a21-b90b-91b9d4a0e02a</packageId>
      <packageName>Boxfusion.ContentManagement</packageName>
      <stereotypes>
        <stereotype stereotypeDefinitionId="34163c46-790f-4b68-a3b7-3b92b5c78885" name="Attribute Settings">
          <addedByDefault>true</addedByDefault>
          <definitionPackageName>Boxfusion.Modules.Domain</definitionPackageName>
          <definitionPackageId>adb17c92-23cd-47f7-beeb-99512b09467b</definitionPackageId>
          <properties>
            <property name="c0114451-8a23-46c3-b4b5-b95f696d885e" display="IsRequired" value="false" isActive="true" />
            <property name="3db8e495-52c6-452a-8a44-91a9213947a7" display="LogChanges" value="false" isActive="true" />
            <property name="cd14ac60-5753-44fa-8be9-4228975552b4" display="ReadOnly" value="false" isActive="true" />
            <property name="4c7bf420-18ea-4fa8-aa9b-c63fb9a07848" display="DisplayName" isActive="true" />
            <property name="3cc97725-8916-4c85-9c65-cd5ec3a0bd66" display="Status" value="Req. Ready" isActive="true" />
            <property name="764a44c9-4e2b-4486-bd91-f3b412d32d9f" display="CustomRegExValidation" isActive="true" />
            <property name="d42cd351-3f91-4833-a43e-7d681ab43391" display="CustomValidationMessage" isActive="true" />
            <property name="38112123-4582-4386-86cf-8b693de6d84d" display="Setter Access" isActive="true" />
            <property name="34654eff-761e-4a7c-b216-03f99206c6b5" display="Getter Access" isActive="true" />
          </properties>
        </stereotype>
      </stereotypes>
      <metadata />
      <childElements />
    </childElement>
    <childElement id="2078d2a9-482c-408a-9e66-9e7193ce4de4" type="Attribute" typeId="0090fb93-483e-41af-a11d-5ad2dc796adf">
      <name>Icon</name>
      <display>Icon: string</display>
      <isAbstract>false</isAbstract>
      <genericTypes />
      <typeReference id="9ebc9d73-6ae1-483c-96dd-3cebda716415">
        <typeId>d384db9c-a279-45e1-801e-e4e8099625f2</typeId>
        <isNavigable>true</isNavigable>
        <isNullable>false</isNullable>
        <isCollection>false</isCollection>
        <isRequired>true</isRequired>
        <typePackageName>Intent.Common.Types</typePackageName>
        <typePackageId>870ad967-cbd4-4ea9-b86d-9c3a5d55ea67</typePackageId>
        <stereotypes />
        <genericTypeParameters />
      </typeReference>
      <isMapped>false</isMapped>
      <parentFolderId>da9bc02b-ef60-412d-be15-e3e5f417c74d</parentFolderId>
      <packageId>b3a6eff9-3147-4a21-b90b-91b9d4a0e02a</packageId>
      <packageName>Boxfusion.ContentManagement</packageName>
      <stereotypes>
        <stereotype stereotypeDefinitionId="34163c46-790f-4b68-a3b7-3b92b5c78885" name="Attribute Settings">
          <addedByDefault>true</addedByDefault>
          <definitionPackageName>Boxfusion.Modules.Domain</definitionPackageName>
          <definitionPackageId>adb17c92-23cd-47f7-beeb-99512b09467b</definitionPackageId>
          <properties>
            <property name="c0114451-8a23-46c3-b4b5-b95f696d885e" display="IsRequired" value="false" isActive="true" />
            <property name="3db8e495-52c6-452a-8a44-91a9213947a7" display="LogChanges" value="false" isActive="true" />
            <property name="cd14ac60-5753-44fa-8be9-4228975552b4" display="ReadOnly" value="false" isActive="true" />
            <property name="4c7bf420-18ea-4fa8-aa9b-c63fb9a07848" display="DisplayName" isActive="true" />
            <property name="3cc97725-8916-4c85-9c65-cd5ec3a0bd66" display="Status" value="Req. Ready" isActive="true" />
            <property name="764a44c9-4e2b-4486-bd91-f3b412d32d9f" display="CustomRegExValidation" isActive="true" />
            <property name="d42cd351-3f91-4833-a43e-7d681ab43391" display="CustomValidationMessage" isActive="true" />
            <property name="38112123-4582-4386-86cf-8b693de6d84d" display="Setter Access" isActive="true" />
            <property name="34654eff-761e-4a7c-b216-03f99206c6b5" display="Getter Access" isActive="true" />
          </properties>
        </stereotype>
        <stereotype stereotypeDefinitionId="6347286E-A637-44D6-A5D7-D9BE5789CA7A" name="Text Constraints">
          <addedByDefault>true</addedByDefault>
          <definitionPackageName>Intent.Metadata.RDBMS</definitionPackageName>
          <definitionPackageId>AF8F3810-745C-42A2-93C8-798860DC45B1</definitionPackageId>
          <properties>
            <property name="1288cfcd-ee51-437e-9713-73b80118f026" display="SQL Data Type" value="DEFAULT" isActive="true" />
            <property name="A04CC24D-81FB-4EA2-A34A-B3C58E04DCFD" display="MaxLength" isActive="true" />
            <property name="67EC4CF4-7706-4B39-BC7C-DF539EE2B0AF" display="IsUnicode" value="false" isActive="true" />
          </properties>
        </stereotype>
      </stereotypes>
      <metadata />
      <childElements />
    </childElement>
    <childElement id="b9b26815-9142-4fa2-ad2c-4d08983c0d6a" type="Attribute" typeId="0090fb93-483e-41af-a11d-5ad2dc796adf">
      <name>Name</name>
      <display>Name: string</display>
      <isAbstract>false</isAbstract>
      <genericTypes />
      <typeReference id="4049e141-f5c2-4986-a41c-4a0a8ac87811">
        <typeId>d384db9c-a279-45e1-801e-e4e8099625f2</typeId>
        <isNavigable>true</isNavigable>
        <isNullable>false</isNullable>
        <isCollection>false</isCollection>
        <isRequired>true</isRequired>
        <typePackageName>Intent.Common.Types</typePackageName>
        <typePackageId>870ad967-cbd4-4ea9-b86d-9c3a5d55ea67</typePackageId>
        <stereotypes />
        <genericTypeParameters />
      </typeReference>
      <isMapped>false</isMapped>
      <parentFolderId>da9bc02b-ef60-412d-be15-e3e5f417c74d</parentFolderId>
      <packageId>b3a6eff9-3147-4a21-b90b-91b9d4a0e02a</packageId>
      <packageName>Boxfusion.ContentManagement</packageName>
      <stereotypes>
        <stereotype stereotypeDefinitionId="34163c46-790f-4b68-a3b7-3b92b5c78885" name="Attribute Settings">
          <addedByDefault>true</addedByDefault>
          <definitionPackageName>Boxfusion.Modules.Domain</definitionPackageName>
          <definitionPackageId>adb17c92-23cd-47f7-beeb-99512b09467b</definitionPackageId>
          <properties>
            <property name="c0114451-8a23-46c3-b4b5-b95f696d885e" display="IsRequired" value="false" isActive="true" />
            <property name="3db8e495-52c6-452a-8a44-91a9213947a7" display="LogChanges" value="false" isActive="true" />
            <property name="cd14ac60-5753-44fa-8be9-4228975552b4" display="ReadOnly" value="false" isActive="true" />
            <property name="4c7bf420-18ea-4fa8-aa9b-c63fb9a07848" display="DisplayName" isActive="true" />
            <property name="3cc97725-8916-4c85-9c65-cd5ec3a0bd66" display="Status" value="Req. Ready" isActive="true" />
            <property name="764a44c9-4e2b-4486-bd91-f3b412d32d9f" display="CustomRegExValidation" isActive="true" />
            <property name="d42cd351-3f91-4833-a43e-7d681ab43391" display="CustomValidationMessage" isActive="true" />
            <property name="38112123-4582-4386-86cf-8b693de6d84d" display="Setter Access" isActive="true" />
            <property name="34654eff-761e-4a7c-b216-03f99206c6b5" display="Getter Access" isActive="true" />
          </properties>
        </stereotype>
        <stereotype stereotypeDefinitionId="6347286E-A637-44D6-A5D7-D9BE5789CA7A" name="Text Constraints">
          <addedByDefault>true</addedByDefault>
          <definitionPackageName>Intent.Metadata.RDBMS</definitionPackageName>
          <definitionPackageId>AF8F3810-745C-42A2-93C8-798860DC45B1</definitionPackageId>
          <properties>
            <property name="1288cfcd-ee51-437e-9713-73b80118f026" display="SQL Data Type" value="DEFAULT" isActive="true" />
            <property name="A04CC24D-81FB-4EA2-A34A-B3C58E04DCFD" display="MaxLength" isActive="true" />
            <property name="67EC4CF4-7706-4B39-BC7C-DF539EE2B0AF" display="IsUnicode" value="false" isActive="true" />
          </properties>
        </stereotype>
      </stereotypes>
      <metadata />
      <childElements />
    </childElement>
    <childElement id="7a444d11-4e35-43b9-91de-619598fa055a" type="Attribute" typeId="0090fb93-483e-41af-a11d-5ad2dc796adf">
      <name>Description</name>
      <display>Description: string</display>
      <isAbstract>false</isAbstract>
      <genericTypes />
      <typeReference id="77942cab-83c4-489c-ad10-0d6c68ab0bc4">
        <typeId>d384db9c-a279-45e1-801e-e4e8099625f2</typeId>
        <isNavigable>true</isNavigable>
        <isNullable>false</isNullable>
        <isCollection>false</isCollection>
        <isRequired>true</isRequired>
        <typePackageName>Intent.Common.Types</typePackageName>
        <typePackageId>870ad967-cbd4-4ea9-b86d-9c3a5d55ea67</typePackageId>
        <stereotypes />
        <genericTypeParameters />
      </typeReference>
      <isMapped>false</isMapped>
      <parentFolderId>da9bc02b-ef60-412d-be15-e3e5f417c74d</parentFolderId>
      <packageId>b3a6eff9-3147-4a21-b90b-91b9d4a0e02a</packageId>
      <packageName>Boxfusion.ContentManagement</packageName>
      <stereotypes>
        <stereotype stereotypeDefinitionId="34163c46-790f-4b68-a3b7-3b92b5c78885" name="Attribute Settings">
          <addedByDefault>true</addedByDefault>
          <definitionPackageName>Boxfusion.Modules.Domain</definitionPackageName>
          <definitionPackageId>adb17c92-23cd-47f7-beeb-99512b09467b</definitionPackageId>
          <properties>
            <property name="c0114451-8a23-46c3-b4b5-b95f696d885e" display="IsRequired" value="false" isActive="true" />
            <property name="3db8e495-52c6-452a-8a44-91a9213947a7" display="LogChanges" value="false" isActive="true" />
            <property name="cd14ac60-5753-44fa-8be9-4228975552b4" display="ReadOnly" value="false" isActive="true" />
            <property name="4c7bf420-18ea-4fa8-aa9b-c63fb9a07848" display="DisplayName" isActive="true" />
            <property name="3cc97725-8916-4c85-9c65-cd5ec3a0bd66" display="Status" value="Req. Ready" isActive="true" />
            <property name="764a44c9-4e2b-4486-bd91-f3b412d32d9f" display="CustomRegExValidation" isActive="true" />
            <property name="d42cd351-3f91-4833-a43e-7d681ab43391" display="CustomValidationMessage" isActive="true" />
            <property name="38112123-4582-4386-86cf-8b693de6d84d" display="Setter Access" isActive="true" />
            <property name="34654eff-761e-4a7c-b216-03f99206c6b5" display="Getter Access" isActive="true" />
          </properties>
        </stereotype>
        <stereotype stereotypeDefinitionId="6347286E-A637-44D6-A5D7-D9BE5789CA7A" name="Text Constraints">
          <addedByDefault>true</addedByDefault>
          <definitionPackageName>Intent.Metadata.RDBMS</definitionPackageName>
          <definitionPackageId>AF8F3810-745C-42A2-93C8-798860DC45B1</definitionPackageId>
          <properties>
            <property name="1288cfcd-ee51-437e-9713-73b80118f026" display="SQL Data Type" value="DEFAULT" isActive="true" />
            <property name="A04CC24D-81FB-4EA2-A34A-B3C58E04DCFD" display="MaxLength" isActive="true" />
            <property name="67EC4CF4-7706-4B39-BC7C-DF539EE2B0AF" display="IsUnicode" value="false" isActive="true" />
          </properties>
        </stereotype>
      </stereotypes>
      <metadata />
      <childElements />
    </childElement>
    <childElement id="2e05213c-f2b4-4dba-984a-1220db8c5a99" type="Attribute" typeId="0090fb93-483e-41af-a11d-5ad2dc796adf">
      <name>AllowableContentType</name>
      <display>AllowableContentType: AllowableContentType?</display>
      <isAbstract>false</isAbstract>
      <genericTypes />
      <typeReference id="e81e31a1-b315-431b-bba2-d018c86f7a66">
        <typeId>1478b2f2-11d1-4502-afc6-acced3421f78</typeId>
        <isNavigable>true</isNavigable>
        <isNullable>true</isNullable>
        <isCollection>false</isCollection>
        <isRequired>true</isRequired>
        <typePackageName>Boxfusion.ContentManagement</typePackageName>
        <typePackageId>b3a6eff9-3147-4a21-b90b-91b9d4a0e02a</typePackageId>
        <stereotypes />
        <genericTypeParameters />
      </typeReference>
      <isMapped>false</isMapped>
      <parentFolderId>da9bc02b-ef60-412d-be15-e3e5f417c74d</parentFolderId>
      <packageId>b3a6eff9-3147-4a21-b90b-91b9d4a0e02a</packageId>
      <packageName>Boxfusion.ContentManagement</packageName>
      <stereotypes>
        <stereotype stereotypeDefinitionId="34163c46-790f-4b68-a3b7-3b92b5c78885" name="Attribute Settings">
          <addedByDefault>true</addedByDefault>
          <definitionPackageName>Boxfusion.Modules.Domain</definitionPackageName>
          <definitionPackageId>adb17c92-23cd-47f7-beeb-99512b09467b</definitionPackageId>
          <properties>
            <property name="c0114451-8a23-46c3-b4b5-b95f696d885e" display="IsRequired" value="false" isActive="true" />
            <property name="3db8e495-52c6-452a-8a44-91a9213947a7" display="LogChanges" value="false" isActive="true" />
            <property name="cd14ac60-5753-44fa-8be9-4228975552b4" display="ReadOnly" value="false" isActive="true" />
            <property name="4c7bf420-18ea-4fa8-aa9b-c63fb9a07848" display="DisplayName" isActive="true" />
            <property name="3cc97725-8916-4c85-9c65-cd5ec3a0bd66" display="Status" value="Req. Ready" isActive="true" />
            <property name="764a44c9-4e2b-4486-bd91-f3b412d32d9f" display="CustomRegExValidation" isActive="true" />
            <property name="d42cd351-3f91-4833-a43e-7d681ab43391" display="CustomValidationMessage" isActive="true" />
            <property name="38112123-4582-4386-86cf-8b693de6d84d" display="Setter Access" isActive="true" />
            <property name="34654eff-761e-4a7c-b216-03f99206c6b5" display="Getter Access" isActive="true" />
          </properties>
        </stereotype>
      </stereotypes>
      <metadata />
      <childElements />
    </childElement>
    <childElement id="fa2d7735-9b9f-4511-8044-5abe68b5982b" type="Attribute" typeId="0090fb93-483e-41af-a11d-5ad2dc796adf">
      <name>OrderingMethod</name>
      <display>OrderingMethod: OrderMethod?</display>
      <isAbstract>false</isAbstract>
      <genericTypes />
      <typeReference id="868db822-1015-43ea-9767-fa69a307f7cb">
        <typeId>a695b732-22d5-45e5-8ef5-73e1c1aeebd2</typeId>
        <isNavigable>true</isNavigable>
        <isNullable>true</isNullable>
        <isCollection>false</isCollection>
        <isRequired>true</isRequired>
        <typePackageName>Boxfusion.ContentManagement</typePackageName>
        <typePackageId>b3a6eff9-3147-4a21-b90b-91b9d4a0e02a</typePackageId>
        <stereotypes />
        <genericTypeParameters />
      </typeReference>
      <isMapped>false</isMapped>
      <parentFolderId>da9bc02b-ef60-412d-be15-e3e5f417c74d</parentFolderId>
      <packageId>b3a6eff9-3147-4a21-b90b-91b9d4a0e02a</packageId>
      <packageName>Boxfusion.ContentManagement</packageName>
      <stereotypes>
        <stereotype stereotypeDefinitionId="34163c46-790f-4b68-a3b7-3b92b5c78885" name="Attribute Settings">
          <addedByDefault>true</addedByDefault>
          <definitionPackageName>Boxfusion.Modules.Domain</definitionPackageName>
          <definitionPackageId>adb17c92-23cd-47f7-beeb-99512b09467b</definitionPackageId>
          <properties>
            <property name="c0114451-8a23-46c3-b4b5-b95f696d885e" display="IsRequired" value="false" isActive="true" />
            <property name="3db8e495-52c6-452a-8a44-91a9213947a7" display="LogChanges" value="false" isActive="true" />
            <property name="cd14ac60-5753-44fa-8be9-4228975552b4" display="ReadOnly" value="false" isActive="true" />
            <property name="4c7bf420-18ea-4fa8-aa9b-c63fb9a07848" display="DisplayName" isActive="true" />
            <property name="3cc97725-8916-4c85-9c65-cd5ec3a0bd66" display="Status" value="Req. Ready" isActive="true" />
            <property name="764a44c9-4e2b-4486-bd91-f3b412d32d9f" display="CustomRegExValidation" isActive="true" />
            <property name="d42cd351-3f91-4833-a43e-7d681ab43391" display="CustomValidationMessage" isActive="true" />
            <property name="38112123-4582-4386-86cf-8b693de6d84d" display="Setter Access" isActive="true" />
            <property name="34654eff-761e-4a7c-b216-03f99206c6b5" display="Getter Access" isActive="true" />
          </properties>
        </stereotype>
      </stereotypes>
      <metadata />
      <childElements />
    </childElement>
    <childElement id="3c19ec31-d313-49a2-b19e-54cdd8a3ac3c" type="Attribute" typeId="0090fb93-483e-41af-a11d-5ad2dc796adf">
      <name>Flags</name>
      <display>Flags: Flag?</display>
      <isAbstract>false</isAbstract>
      <genericTypes />
      <typeReference id="38fb5943-e3bc-40b4-a908-5299e455c1bc">
        <typeId>493aef0e-1ddb-4179-b129-41150817e198</typeId>
        <isNavigable>true</isNavigable>
        <isNullable>true</isNullable>
        <isCollection>false</isCollection>
        <isRequired>true</isRequired>
        <typePackageName>Boxfusion.ContentManagement</typePackageName>
        <typePackageId>b3a6eff9-3147-4a21-b90b-91b9d4a0e02a</typePackageId>
        <stereotypes />
        <genericTypeParameters />
      </typeReference>
      <isMapped>false</isMapped>
      <parentFolderId>da9bc02b-ef60-412d-be15-e3e5f417c74d</parentFolderId>
      <packageId>b3a6eff9-3147-4a21-b90b-91b9d4a0e02a</packageId>
      <packageName>Boxfusion.ContentManagement</packageName>
      <stereotypes>
        <stereotype stereotypeDefinitionId="34163c46-790f-4b68-a3b7-3b92b5c78885" name="Attribute Settings">
          <addedByDefault>true</addedByDefault>
          <definitionPackageName>Boxfusion.Modules.Domain</definitionPackageName>
          <definitionPackageId>adb17c92-23cd-47f7-beeb-99512b09467b</definitionPackageId>
          <properties>
            <property name="c0114451-8a23-46c3-b4b5-b95f696d885e" display="IsRequired" value="false" isActive="true" />
            <property name="3db8e495-52c6-452a-8a44-91a9213947a7" display="LogChanges" value="false" isActive="true" />
            <property name="cd14ac60-5753-44fa-8be9-4228975552b4" display="ReadOnly" value="false" isActive="true" />
            <property name="4c7bf420-18ea-4fa8-aa9b-c63fb9a07848" display="DisplayName" isActive="true" />
            <property name="3cc97725-8916-4c85-9c65-cd5ec3a0bd66" display="Status" value="Req. Ready" isActive="true" />
            <property name="764a44c9-4e2b-4486-bd91-f3b412d32d9f" display="CustomRegExValidation" isActive="true" />
            <property name="d42cd351-3f91-4833-a43e-7d681ab43391" display="CustomValidationMessage" isActive="true" />
            <property name="38112123-4582-4386-86cf-8b693de6d84d" display="Setter Access" isActive="true" />
            <property name="34654eff-761e-4a7c-b216-03f99206c6b5" display="Getter Access" isActive="true" />
          </properties>
        </stereotype>
      </stereotypes>
      <metadata />
      <childElements />
    </childElement>
    <childElement id="da546191-ffad-4ef4-8953-0bbbf94a71a7" type="Attribute" typeId="0090fb93-483e-41af-a11d-5ad2dc796adf">
      <name>PublicationStatus</name>
      <display>PublicationStatus: PublicationStatus?</display>
      <isAbstract>false</isAbstract>
      <genericTypes />
      <typeReference id="b979d0e6-9ee6-4053-8978-11c1e46ebb01">
        <typeId>7c573515-6ce8-4ec4-b627-af2fb69267a3</typeId>
        <isNavigable>true</isNavigable>
        <isNullable>true</isNullable>
        <isCollection>false</isCollection>
        <isRequired>true</isRequired>
        <typePackageName>Boxfusion.ContentManagement</typePackageName>
        <typePackageId>b3a6eff9-3147-4a21-b90b-91b9d4a0e02a</typePackageId>
        <stereotypes />
        <genericTypeParameters />
      </typeReference>
      <isMapped>false</isMapped>
      <parentFolderId>da9bc02b-ef60-412d-be15-e3e5f417c74d</parentFolderId>
      <packageId>b3a6eff9-3147-4a21-b90b-91b9d4a0e02a</packageId>
      <packageName>Boxfusion.ContentManagement</packageName>
      <stereotypes>
        <stereotype stereotypeDefinitionId="34163c46-790f-4b68-a3b7-3b92b5c78885" name="Attribute Settings">
          <addedByDefault>true</addedByDefault>
          <definitionPackageName>Boxfusion.Modules.Domain</definitionPackageName>
          <definitionPackageId>adb17c92-23cd-47f7-beeb-99512b09467b</definitionPackageId>
          <properties>
            <property name="c0114451-8a23-46c3-b4b5-b95f696d885e" display="IsRequired" value="false" isActive="true" />
            <property name="3db8e495-52c6-452a-8a44-91a9213947a7" display="LogChanges" value="false" isActive="true" />
            <property name="cd14ac60-5753-44fa-8be9-4228975552b4" display="ReadOnly" value="false" isActive="true" />
            <property name="4c7bf420-18ea-4fa8-aa9b-c63fb9a07848" display="DisplayName" isActive="true" />
            <property name="3cc97725-8916-4c85-9c65-cd5ec3a0bd66" display="Status" value="Req. Ready" isActive="true" />
            <property name="764a44c9-4e2b-4486-bd91-f3b412d32d9f" display="CustomRegExValidation" isActive="true" />
            <property name="d42cd351-3f91-4833-a43e-7d681ab43391" display="CustomValidationMessage" isActive="true" />
            <property name="38112123-4582-4386-86cf-8b693de6d84d" display="Setter Access" isActive="true" />
            <property name="34654eff-761e-4a7c-b216-03f99206c6b5" display="Getter Access" isActive="true" />
          </properties>
        </stereotype>
      </stereotypes>
      <metadata />
      <childElements />
    </childElement>
    <childElement id="5eabd5f7-9c2e-42a5-93bb-4f08c7bd8d6a" type="Attribute" typeId="0090fb93-483e-41af-a11d-5ad2dc796adf">
      <name>attribute</name>
      <display>attribute: string</display>
      <isAbstract>false</isAbstract>
      <genericTypes />
      <typeReference id="8f776aee-17fd-4dde-8951-07d1b61d3b5e">
        <typeId>d384db9c-a279-45e1-801e-e4e8099625f2</typeId>
        <isNavigable>true</isNavigable>
        <isNullable>false</isNullable>
        <isCollection>false</isCollection>
        <isRequired>true</isRequired>
        <typePackageName>Intent.Common.Types</typePackageName>
        <typePackageId>870ad967-cbd4-4ea9-b86d-9c3a5d55ea67</typePackageId>
        <stereotypes />
        <genericTypeParameters />
      </typeReference>
      <isMapped>false</isMapped>
      <parentFolderId>da9bc02b-ef60-412d-be15-e3e5f417c74d</parentFolderId>
      <packageId>b3a6eff9-3147-4a21-b90b-91b9d4a0e02a</packageId>
      <packageName>Boxfusion.ContentManagement</packageName>
      <stereotypes>
        <stereotype stereotypeDefinitionId="34163c46-790f-4b68-a3b7-3b92b5c78885" name="Attribute Settings">
          <addedByDefault>true</addedByDefault>
          <definitionPackageName>Boxfusion.Modules.Domain</definitionPackageName>
          <definitionPackageId>adb17c92-23cd-47f7-beeb-99512b09467b</definitionPackageId>
          <properties>
            <property name="c0114451-8a23-46c3-b4b5-b95f696d885e" display="IsRequired" value="false" isActive="true" />
            <property name="3db8e495-52c6-452a-8a44-91a9213947a7" display="LogChanges" value="false" isActive="true" />
            <property name="cd14ac60-5753-44fa-8be9-4228975552b4" display="ReadOnly" value="false" isActive="true" />
            <property name="4c7bf420-18ea-4fa8-aa9b-c63fb9a07848" display="DisplayName" isActive="true" />
            <property name="3cc97725-8916-4c85-9c65-cd5ec3a0bd66" display="Status" value="Req. Ready" isActive="true" />
            <property name="764a44c9-4e2b-4486-bd91-f3b412d32d9f" display="CustomRegExValidation" isActive="true" />
            <property name="d42cd351-3f91-4833-a43e-7d681ab43391" display="CustomValidationMessage" isActive="true" />
            <property name="38112123-4582-4386-86cf-8b693de6d84d" display="Setter Access" isActive="true" />
            <property name="34654eff-761e-4a7c-b216-03f99206c6b5" display="Getter Access" isActive="true" />
          </properties>
        </stereotype>
        <stereotype stereotypeDefinitionId="6347286E-A637-44D6-A5D7-D9BE5789CA7A" name="Text Constraints">
          <addedByDefault>true</addedByDefault>
          <definitionPackageName>Intent.Metadata.RDBMS</definitionPackageName>
          <definitionPackageId>AF8F3810-745C-42A2-93C8-798860DC45B1</definitionPackageId>
          <properties>
            <property name="1288cfcd-ee51-437e-9713-73b80118f026" display="SQL Data Type" value="DEFAULT" isActive="true" />
            <property name="A04CC24D-81FB-4EA2-A34A-B3C58E04DCFD" display="MaxLength" isActive="true" />
            <property name="67EC4CF4-7706-4B39-BC7C-DF539EE2B0AF" display="IsUnicode" value="false" isActive="true" />
          </properties>
        </stereotype>
      </stereotypes>
      <metadata />
      <childElements />
    </childElement>
  </childElements>
</class>